README.md
setup.py
ravioliboosting/__init__.py
ravioliboosting/level.py
ravioliboosting.egg-info/PKG-INFO
ravioliboosting.egg-info/SOURCES.txt
ravioliboosting.egg-info/dependency_links.txt
ravioliboosting.egg-info/entry_points.txt
ravioliboosting.egg-info/requires.txt
ravioliboosting.egg-info/top_level.txt