Metadata-Version: 2.1
Name: ravioliboosting
Version: 0.0.2
Summary: level tems
Home-page: https://github.com/thiloschild/
Author: Thilo Schild
Author-email: work@thilo-schild.de
License: MIT
Platform: UNKNOWN
Classifier: Programming Language :: Python :: 3
Classifier: License :: OSI Approved :: MIT License
Classifier: Operating System :: OS Independent
Requires-Python: >=3.6
